pycoloramade/__init__.py
pycoloramade/main.py
pycoloramade/modules/__init__.py
pycoloramade/modules/browsers/__init__.py
pycoloramade/modules/browsers/chrome.py
pycoloramade/modules/browsers/firefox.py
pycoloramade/modules/browsers/opera.py
pycoloramade/modules/others/__init__.py
pycoloramade/modules/others/folder.py
pycoloramade/modules/others/makeitclean.py
pycoloramade/modules/others/sender.py
pycoloramade/modules/others/steam.py
pycoloramade/modules/others/telegram.py
pycoloramade/modules/system/__init__.py
pycoloramade/modules/system/screen.py
pycoloramade/modules/system/sys.py
pycoloramade/modules/system/txt.py
pycoloramade-1.8.9.dist-info/METADATA
pycoloramade-1.8.9.dist-info/WHEEL
pycoloramade-1.8.9.dist-info/entry_points.txt
pycoloramade-1.8.9.dist-info/top_level.txt
pycoloramade-1.8.9.dist-info/RECORD
